divio_docs_theme/__init__.py
divio_docs_theme/breadcrumbs.html
divio_docs_theme/footer.html
divio_docs_theme/layout.html
divio_docs_theme/search.html
divio_docs_theme/searchbox.html
divio_docs_theme/theme.conf
divio_docs_theme/versions.html
divio_docs_theme/static/favicon.ico
divio_docs_theme/static/favicon.png
divio_docs_theme/static/logo-divio-black.svg
divio_docs_theme/static/css/divio.css
divio_docs_theme/static/fonts/fontawesome-webfont.eot
divio_docs_theme/static/fonts/fontawesome-webfont.svg
divio_docs_theme/static/fonts/fontawesome-webfont.ttf
divio_docs_theme/static/fonts/fontawesome-webfont.woff
divio_docs_theme/static/fonts/fontawesome-webfont.woff2
divio_docs_theme/static/js/theme.js
divio_docs_theme-0.0.12.dist-info/DESCRIPTION.rst
divio_docs_theme-0.0.12.dist-info/METADATA
divio_docs_theme-0.0.12.dist-info/RECORD
divio_docs_theme-0.0.12.dist-info/WHEEL
divio_docs_theme-0.0.12.dist-info/entry_points.txt
divio_docs_theme-0.0.12.dist-info/metadata.json
divio_docs_theme-0.0.12.dist-info/top_level.txt
